{"pageNumber":311,"ayahs":[{"verseKey":"19:77","surah":19,"ayah":77,"text":"أَفَرَأَيْتَ الَّذِي كَفَرَ بِآيَاتِنَا وَقَالَ لَأُوتَيَنَّ مَالًا وَوَلَدًا"},{"verseKey":"19:78","surah":19,"ayah":78,"text":"أَطَّلَعَ الْغَيْبَ أَمِ اتَّخَذَ عِنْدَ الرَّحْمَٰنِ عَهْدًا"},{"verseKey":"19:79","surah":19,"ayah":79,"text":"كَلَّا ۚ سَنَكْتُبُ مَا يَقُولُ وَنَمُدُّ لَهُ مِنَ الْعَذَابِ مَدًّا"},{"verseKey":"19:80","surah":19,"ayah":80,"text":"وَنَرِثُهُ مَا يَقُولُ وَيَأْتِينَا فَرْدًا"},{"verseKey":"19:81","surah":19,"ayah":81,"text":"وَاتَّخَذُوا مِنْ دُونِ اللَّهِ آلِهَةً لِيَكُونُوا لَهُمْ عِزًّا"},{"verseKey":"19:82","surah":19,"ayah":82,"text":"كَلَّا ۚ سَيَكْفُرُونَ بِعِبَادَتِهِمْ وَيَكُونُونَ عَلَيْهِمْ ضِدًّا"},{"verseKey":"19:83","surah":19,"ayah":83,"text":"أَلَمْ تَرَ أَنَّا أَرْسَلْنَا الشَّيَاطِينَ عَلَى الْكَافِرِينَ تَؤُزُّهُمْ أَزًّا"},{"verseKey":"19:84","surah":19,"ayah":84,"text":"فَلَا تَعْجَلْ عَلَيْهِمْ ۖ إِنَّمَا نَعُدُّ لَهُمْ عَدًّا"},{"verseKey":"19:85","surah":19,"ayah":85,"text":"يَوْمَ نَحْشُرُ الْمُتَّقِينَ إِلَى الرَّحْمَٰنِ وَفْدًا"},{"verseKey":"19:86","surah":19,"ayah":86,"text":"وَنَسُوقُ الْمُجْرِمِينَ إِلَىٰ جَهَنَّمَ وِرْدًا"},{"verseKey":"19:87","surah":19,"ayah":87,"text":"لَا يَمْلِكُونَ الشَّفَاعَةَ إِلَّا مَنِ اتَّخَذَ عِنْدَ الرَّحْمَٰنِ عَهْدًا"},{"verseKey":"19:88","surah":19,"ayah":88,"text":"وَقَالُوا اتَّخَذَ الرَّحْمَٰنُ وَلَدًا"},{"verseKey":"19:89","surah":19,"ayah":89,"text":"لَقَدْ جِئْتُمْ شَيْئًا إِدًّا"},{"verseKey":"19:90","surah":19,"ayah":90,"text":"تَكَادُ السَّمَاوَاتُ يَتَفَطَّرْنَ مِنْهُ وَتَنْشَقُّ الْأَرْضُ وَتَخِرُّ الْجِبَالُ هَدًّا"},{"verseKey":"19:91","surah":19,"ayah":91,"text":"أَنْ دَعَوْا لِلرَّحْمَٰنِ وَلَدًا"},{"verseKey":"19:92","surah":19,"ayah":92,"text":"وَمَا يَنْبَغِي لِلرَّحْمَٰنِ أَنْ يَتَّخِذَ وَلَدًا"},{"verseKey":"19:93","surah":19,"ayah":93,"text":"إِنْ كُلُّ مَنْ فِي السَّمَاوَاتِ وَالْأَرْضِ إِلَّا آتِي الرَّحْمَٰنِ عَبْدًا"},{"verseKey":"19:94","surah":19,"ayah":94,"text":"لَقَدْ أَحْصَاهُمْ وَعَدَّهُمْ عَدًّا"},{"verseKey":"19:95","surah":19,"ayah":95,"text":"وَكُلُّهُمْ آتِيهِ يَوْمَ الْقِيَامَةِ فَرْدًا"}]}
